visualization_lib/__init__.py
visualization_lib/visualizer.py
visualization_lib-0.1.dist-info/LICENSE.txt
visualization_lib-0.1.dist-info/METADATA
visualization_lib-0.1.dist-info/WHEEL
visualization_lib-0.1.dist-info/top_level.txt
visualization_lib-0.1.dist-info/RECORD
